{
    "backend": "django",
    "db_name": "",
    "db_pass": "",
    "db_type": "mysql",
    "db_user": "",
    "dbms": "1",
    "description": "generated product",
    "design": "flexy-bootstrap",
    "docker": "0",
    "err_code": 0,
    "frontend": "",
    "github_repo": "https://github.com/appseed-projects/0a18bd37-68d9-4f5b-9b6f-541443b274c2",
    "heroku": "1",
    "pattern": "mvc",
    "pro": "0",
    "task_id": "0a18bd37-68d9-4f5b-9b6f-541443b274c2",
    "task_info": "Upload Sources [0%] - 416 files",
    "task_output": "0a18bd37-68d9-4f5b-9b6f-541443b274c2.zip",
    "task_result": "SUCCESS",
    "task_state": "RUNNING",
    "task_ts_end": "2022-06-06-18-52-11",
    "task_ts_start": "2022-06-06-18-52-08"
}